plus5/__init__.py
plus5-0.1.2.dist-info/LICENSE
plus5-0.1.2.dist-info/METADATA
plus5-0.1.2.dist-info/WHEEL
plus5-0.1.2.dist-info/top_level.txt
plus5-0.1.2.dist-info/RECORD
