Metadata-Version: 2.1
Name: plus5
Version: 0.1.2
Summary: Python port of a subset of the Processing API
Home-page: https://github.com/vrruiz/plus5
Author: Víctor R. Ruiz
Author-email: rvr@linotipo.es
License: UNKNOWN
Platform: UNKNOWN
Classifier: Programming Language :: Python :: 3
Classifier: License :: OSI Approved :: MIT License
Classifier: Operating System :: OS Independent
Requires-Python: >=3.6
Requires-Dist: pygame
